itk_ioscanco-1.0.1.dist-info/RECORD
itk_ioscanco-1.0.1.dist-info/WHEEL
itk_ioscanco-1.0.1.dist-info/METADATA
itk_ioscanco-1.0.1.dist-info/licenses/LICENSE
itk_ioscanco.libs/libtbb-f489fd38.so.12.9
itk/_IOScancoPython.cpython-39-x86_64-linux-gnu.so
itk/IOScancoPython.py
itk/itkScancoImageIOPython.py
itk/Configuration/IOScanco_snake_case.py
itk/Configuration/IOScancoConfig.py
